{"cameraMode":{"drawMode":0,"name":"Shaded","section":"Shading Mode"},"sceneLighting":false,"audioPlay":false,"sceneViewState":{"showFog":true,"showMaterialUpdate":false,"showSkybox":false,"showFlares":true,"showImageEffects":true,"showParticleSystems":true,"showVisualEffectGraphs":true,"m_FxEnabled":true},"in2DMode":false,"pivot":{"x":70.59300994873047,"y":56.97896194458008,"z":16.620908737182618},"rotation":{"x":-0.3017973005771637,"y":0.6707159876823425,"z":-0.3482932448387146,"w":-0.5816708207130432},"size":56.71631622314453,"orthographic":false}